src/__init__.py
src/agent.py
src/routes.py
src/server.py
src/streaming.py
src/tools/__init__.py
src/tools/disk_operations.py
src/tools/web_search.py
maxine-0.1.1.dist-info/entry_points.txt
maxine-0.1.1.dist-info/LICENSE
maxine-0.1.1.dist-info/METADATA
maxine-0.1.1.dist-info/WHEEL
maxine-0.1.1.dist-info/RECORD
