Metadata-Version: 2.3
Name: maxine
Version: 0.1.1
Summary: MAXINE: Multifunctional Agent with eXceptional Intelligence, Nominal Efficiency
Keywords: ai,agent,langchain,ollama
Author: Omar Ahmed
Author-email: omaremadeldin@hotmail.com
Requires-Python: >=3.13,<4.0
Classifier: Development Status :: 3 - Alpha
Classifier: Intended Audience :: Developers
Classifier: License :: OSI Approved :: Apache Software License
Classifier: Programming Language :: Python :: 3
Classifier: Programming Language :: Python :: 3.13
Requires-Dist: aiofiles (>=24.1.0,<25.0.0)
Requires-Dist: aiohttp (>=3.10.0,<4.0.0)
Requires-Dist: beautifulsoup4 (>=4.13.4,<5.0.0)
Requires-Dist: fastapi (>=0.116.0,<0.120.0)
Requires-Dist: httpx (>=0.28.1,<1.0.0)
Requires-Dist: langchain (>=0.3.26,<0.4.0)
Requires-Dist: langchain-community (>=0.3.27,<0.4.0)
Requires-Dist: langchain-experimental (>=0.3.4,<0.4.0)
Requires-Dist: langchain-ollama (>=0.3.3,<0.4.0)
Requires-Dist: langserve[all] (>=0.3.1,<0.4.0)
Requires-Dist: orjson (>=3.10.0,<4.0.0)
Requires-Dist: requests (>=2.32.4,<3.0.0)
Requires-Dist: uvicorn (==0.35.0)
Project-URL: Homepage, https://github.com/anaeldocyaklab/maxine
Project-URL: Repository, https://github.com/anaeldocyaklab/maxine
